odoo/addons/oca_event_badge/CONTRIBUTORS.rst
odoo/addons/oca_event_badge/CREDITS.rst
odoo/addons/oca_event_badge/DESCRIPTION.rst
odoo/addons/oca_event_badge/USAGE.rst
odoo/addons/oca_event_badge/__init__.py
odoo/addons/oca_event_badge/__manifest__.py
odoo/addons/oca_event_badge/static/description/icon.png
odoo/addons/oca_event_badge/static/src/css/event_event_template.css
odoo/addons/oca_event_badge/static/src/img/oca_board.png
odoo/addons/oca_event_badge/static/src/img/oca_delegate.png
odoo/addons/oca_event_badge/static/src/img/oca_member.png
odoo/addons/oca_event_badge/views/event_event_template_asset_report.xml
odoo/addons/oca_event_badge/views/event_event_templates.xml
odoo11_addon_oca_event_badge-11.0.1.0.0.dist-info/METADATA
odoo11_addon_oca_event_badge-11.0.1.0.0.dist-info/WHEEL
odoo11_addon_oca_event_badge-11.0.1.0.0.dist-info/top_level.txt
odoo11_addon_oca_event_badge-11.0.1.0.0.dist-info/RECORD
